wadu.py
wadu-0.0.1.dist-info/METADATA
wadu-0.0.1.dist-info/UNLICENSE
wadu-0.0.1.dist-info/WHEEL
wadu-0.0.1.dist-info/top_level.txt
wadu-0.0.1.dist-info/RECORD
