Metadata-Version: 2.1
Name: wadu
Version: 0.0.1
Summary: Recurrence rules for calendar events
Home-page: https://github.com/christophercrouzet/wadu
Author: Christopher Crouzet
Author-email: christopher.crouzet@gmail.com
License: Unlicense
Keywords: wadu recurrence rule date time
Platform: UNKNOWN
Classifier: Development Status :: 4 - Beta
Classifier: Intended Audience :: Developers
Classifier: Operating System :: OS Independent
Classifier: Programming Language :: Python
Classifier: Programming Language :: Python :: 2
Classifier: Programming Language :: Python :: 2.7
Classifier: Programming Language :: Python :: 3
Classifier: Topic :: Software Development :: Libraries :: Python Modules
Classifier: Topic :: Utilities
